shapelets/__init__.py
shapelets/__main__.py
shapelets/shapelets.py
shapelets/dsl/__init__.py
shapelets/dsl/argument_types.py
shapelets/dsl/connection.py
shapelets/dsl/connector.py
shapelets/dsl/data_app.py
shapelets/dsl/data_app_colors.py
shapelets/dsl/data_app_context.py
shapelets/dsl/data_app_events.py
shapelets/dsl/data_app_panel.py
shapelets/dsl/data_app_widgets.py
shapelets/dsl/dsl_op.py
shapelets/dsl/exceptions.py
shapelets/dsl/graph.py
shapelets/dsl/link.py
shapelets/dsl/node.py
shapelets/dsl/resources/function_impl_tpt.jinja
shapelets/model/__init__.py
shapelets/model/capsule.py
shapelets/model/collection.py
shapelets/model/dataframe.py
shapelets/model/exceptions.py
shapelets/model/function_description.py
shapelets/model/function_parameter.py
shapelets/model/group.py
shapelets/model/image.py
shapelets/model/metadata_item.py
shapelets/model/model.py
shapelets/model/ndarray.py
shapelets/model/permissions.py
shapelets/model/replicated_param.py
shapelets/model/sequence.py
shapelets/model/sequence_axis.py
shapelets/model/user.py
shapelets/model/view_match.py
shapelets/services/__init__.py
shapelets/services/base_service.py
shapelets/services/collections_service.py
shapelets/services/data_app_service.py
shapelets/services/dataframe_service.py
shapelets/services/exceptions.py
shapelets/services/execution_service.py
shapelets/services/functions_service.py
shapelets/services/login_service.py
shapelets/services/login_service_support.py
shapelets/services/metadata_service.py
shapelets/services/model_service.py
shapelets/services/ndarrays_service.py
shapelets/services/py2backend_type_adapter.py
shapelets/services/sequences_service.py
shapelets/services/test_service.py
shapelets/services/users_service.py
tests/integration_tests/__init__.py
tests/integration_tests/test_capsules.py
tests/integration_tests/test_collection_tests.py
tests/integration_tests/test_compatible_types_flow.py
tests/integration_tests/test_data_app_service.py
shapelets_solo-0.5.2.dist-info/LICENSE.txt
shapelets_solo-0.5.2.dist-info/METADATA
shapelets_solo-0.5.2.dist-info/WHEEL
shapelets_solo-0.5.2.dist-info/top_level.txt
shapelets_solo-0.5.2.dist-info/RECORD
