Metadata-Version: 2.1
Name: shapelets-solo
Version: 0.5.2
Summary: Python client for Shapelets
Home-page: http://shapelets.io
Author: Shapelets.io
Author-email: info@shapelets.io
License: Shapelets-License
Keywords: time-series platform,time-series analytics,GPU acceleration,Compute Graphs,interactive visualization,Data-Apps
Platform: UNKNOWN
Classifier: Programming Language :: Python :: 3.7
Classifier: Programming Language :: Python :: 3.8
Classifier: Operating System :: Microsoft :: Windows
Classifier: Intended Audience :: Science/Research
Classifier: Topic :: Scientific/Engineering
Classifier: Topic :: Scientific/Engineering :: Visualization
License-File: LICENSE.txt
Requires-Dist: astroid (==2.6.4)
Requires-Dist: cloudpickle (==1.6.0)
Requires-Dist: dill (==0.3.4)
Requires-Dist: jinja2 (==3.0.1)
Requires-Dist: libnacl (==1.8.0)
Requires-Dist: matplotlib (==3.4.2)
Requires-Dist: nest-asyncio (==1.5.1)
Requires-Dist: numpy (==1.21.1)
Requires-Dist: pandas (==1.3.0)
Requires-Dist: pyarrow (==4.0.1)
Requires-Dist: pygeohash (==1.2.0)
Requires-Dist: pylint (==2.9.3)
Requires-Dist: pynacl (==1.4.0)
Requires-Dist: python-dateutil (==2.8.2)
Requires-Dist: pytz (==2021.1)
Requires-Dist: requests (==2.26.0)
Requires-Dist: seaborn (==0.11.1)
Requires-Dist: setuptools (==57.4.0)
Requires-Dist: tqdm (==4.61.2)
Requires-Dist: urllib3 (==1.26.6)
Requires-Dist: psutil (==5.8.0)
